{
  "annotations": {
    "list": [
      {
        "builtIn": 1,
        "datasource": {
          "type": "prometheus",
          "uid": "$${datasource}"
        },
        "enable": true,
        "hide": true,
        "iconColor": "rgba(0, 211, 255, 1)",
        "name": "Annotations & Alerts",
        "type": "dashboard"
      }
    ]
  },
  "editable": true,
  "fiscalYearStartMonth": 0,
  "graphTooltip": 0,
  "id": 122,
  "links": [],
  "panels": [
    {
      "datasource": {
        "type": "prometheus",
        "uid": "$${datasource}"
      },
      "fieldConfig": {
        "defaults": {
          "color": {
            "mode": "palette-classic"
          },
          "custom": {
            "axisBorderShow": false,
            "axisCenteredZero": false,
            "axisColorMode": "text",
            "axisLabel": "",
            "axisPlacement": "auto",
            "barAlignment": 0,
            "barWidthFactor": 0.6,
            "drawStyle": "line",
            "fillOpacity": 30,
            "gradientMode": "none",
            "hideFrom": {
              "legend": false,
              "tooltip": false,
              "viz": false
            },
            "insertNulls": false,
            "lineInterpolation": "linear",
            "lineWidth": 2,
            "pointSize": 5,
            "scaleDistribution": {
              "type": "linear"
            },
            "showPoints": "never",
            "spanNulls": true,
            "stacking": {
              "group": "A",
              "mode": "none"
            },
            "thresholdsStyle": {
              "mode": "off"
            }
          },
          "mappings": [],
          "thresholds": {
            "mode": "absolute",
            "steps": [
              {
                "color": "green"
              },
              {
                "color": "red",
                "value": 80
              }
            ]
          },
          "unit": "bps"
        },
        "overrides": []
      },
      "gridPos": {
        "h": 7,
        "w": 8,
        "x": 0,
        "y": 0
      },
      "id": 7,
      "options": {
        "dataLinks": [],
        "legend": {
          "calcs": [],
          "displayMode": "list",
          "placement": "bottom",
          "showLegend": true
        },
        "tooltip": {
          "hideZeros": false,
          "mode": "single",
          "sort": "none"
        }
      },
      "pluginVersion": "12.0.2",
      "targets": [
        {
          "datasource": {
            "type": "prometheus",
            "uid": "$${datasource}"
          },
          "expr": "sum(avi_se_if_avg_bandwidth{instance=~\"$instance\", tenant=~\"$tenant\",type=\"serviceengine\"})",
          "format": "time_series",
          "interval": "1m",
          "intervalFactor": 1,
          "legendFormat": "total bandwidth",
          "refId": "A",
          "target": "alias(sumSeries(network-script.avi.$location.$environment.$device.serviceengine.*.se_if_avg_bandwidth), 'totalbandwidth')",
          "textEditor": false
        }
      ],
      "title": "Total SE Average Bandwidth (5min avg)",
      "type": "timeseries"
    },
    {
      "cacheTimeout": "300",
      "datasource": {
        "type": "prometheus",
        "uid": "$${datasource}"
      },
      "fieldConfig": {
        "defaults": {
          "color": {
            "mode": "palette-classic"
          },
          "custom": {
            "axisBorderShow": false,
            "axisCenteredZero": false,
            "axisColorMode": "text",
            "axisLabel": "",
            "axisPlacement": "auto",
            "barAlignment": 0,
            "barWidthFactor": 0.6,
            "drawStyle": "line",
            "fillOpacity": 10,
            "gradientMode": "none",
            "hideFrom": {
              "legend": false,
              "tooltip": false,
              "viz": false
            },
            "insertNulls": false,
            "lineInterpolation": "linear",
            "lineWidth": 2,
            "pointSize": 5,
            "scaleDistribution": {
              "type": "linear"
            },
            "showPoints": "never",
            "spanNulls": true,
            "stacking": {
              "group": "A",
              "mode": "none"
            },
            "thresholdsStyle": {
              "mode": "off"
            }
          },
          "mappings": [],
          "thresholds": {
            "mode": "absolute",
            "steps": [
              {
                "color": "green"
              },
              {
                "color": "red",
                "value": 80
              }
            ]
          },
          "unit": "bps"
        },
        "overrides": []
      },
      "gridPos": {
        "h": 7,
        "w": 8,
        "x": 8,
        "y": 0
      },
      "id": 4,
      "options": {
        "dataLinks": [],
        "legend": {
          "calcs": [],
          "displayMode": "list",
          "placement": "bottom",
          "showLegend": true
        },
        "tooltip": {
          "hideZeros": false,
          "mode": "multi",
          "sort": "none"
        }
      },
      "pluginVersion": "12.0.2",
      "targets": [
        {
          "datasource": {
            "type": "prometheus",
            "uid": "$${datasource}"
          },
          "expr": "topk(5, avi_se_if_avg_bandwidth{instance=~\"$instance\", tenant=~\"$tenant\",type=\"serviceengine\"})",
          "format": "time_series",
          "interval": "1m",
          "intervalFactor": 1,
          "legendFormat": "{{name}}",
          "refId": "A",
          "target": "aliasByNode(highestMax(network-script.avi.$location.$environment.$device.serviceengine.*.se_if_avg_bandwidth, 5), 6)",
          "textEditor": false
        }
      ],
      "title": "Top 5 SE - Average Bandwidth (5min avg)",
      "type": "timeseries"
    },
    {
      "datasource": {
        "type": "prometheus",
        "uid": "$${datasource}"
      },
      "fieldConfig": {
        "defaults": {
          "color": {
            "mode": "palette-classic"
          },
          "custom": {
            "axisBorderShow": false,
            "axisCenteredZero": false,
            "axisColorMode": "text",
            "axisLabel": "",
            "axisPlacement": "auto",
            "barAlignment": 0,
            "barWidthFactor": 0.6,
            "drawStyle": "line",
            "fillOpacity": 10,
            "gradientMode": "none",
            "hideFrom": {
              "legend": false,
              "tooltip": false,
              "viz": false
            },
            "insertNulls": false,
            "lineInterpolation": "linear",
            "lineWidth": 2,
            "pointSize": 5,
            "scaleDistribution": {
              "type": "linear"
            },
            "showPoints": "never",
            "spanNulls": true,
            "stacking": {
              "group": "A",
              "mode": "none"
            },
            "thresholdsStyle": {
              "mode": "line+area"
            }
          },
          "mappings": [],
          "thresholds": {
            "mode": "absolute",
            "steps": [
              {
                "color": "transparent"
              },
              {
                "color": "red",
                "value": 75
              }
            ]
          },
          "unit": "percent"
        },
        "overrides": []
      },
      "gridPos": {
        "h": 7,
        "w": 8,
        "x": 16,
        "y": 0
      },
      "id": 11,
      "options": {
        "dataLinks": [],
        "legend": {
          "calcs": [],
          "displayMode": "list",
          "placement": "bottom",
          "showLegend": true
        },
        "tooltip": {
          "hideZeros": false,
          "mode": "multi",
          "sort": "none"
        }
      },
      "pluginVersion": "12.0.2",
      "targets": [
        {
          "datasource": {
            "type": "prometheus",
            "uid": "$${datasource}"
          },
          "expr": "topk(5,avi_se_stats_avg_cpu_usage{instance=~\"$instance\", tenant=~\"$tenant\",type=\"serviceengine\"})",
          "format": "time_series",
          "interval": "1m",
          "intervalFactor": 1,
          "legendFormat": "{{name}}",
          "refId": "A",
          "target": "aliasByNode(highestMax(network-script.avi.$location.$environment.$device.serviceengine.*.se_stats_avg_cpu_usage, 5), 6)",
          "textEditor": false
        }
      ],
      "title": "Top 5 - SE CPU%",
      "type": "timeseries"
    },
    {
      "cacheTimeout": "60",
      "datasource": {
        "type": "prometheus",
        "uid": "$${datasource}"
      },
      "fieldConfig": {
        "defaults": {
          "color": {
            "mode": "palette-classic"
          },
          "custom": {
            "axisBorderShow": false,
            "axisCenteredZero": false,
            "axisColorMode": "text",
            "axisLabel": "",
            "axisPlacement": "auto",
            "barAlignment": 0,
            "barWidthFactor": 0.6,
            "drawStyle": "line",
            "fillOpacity": 0,
            "gradientMode": "none",
            "hideFrom": {
              "legend": false,
              "tooltip": false,
              "viz": false
            },
            "insertNulls": false,
            "lineInterpolation": "linear",
            "lineWidth": 2,
            "pointSize": 5,
            "scaleDistribution": {
              "type": "linear"
            },
            "showPoints": "never",
            "spanNulls": true,
            "stacking": {
              "group": "A",
              "mode": "none"
            },
            "thresholdsStyle": {
              "mode": "off"
            }
          },
          "mappings": [],
          "thresholds": {
            "mode": "absolute",
            "steps": [
              {
                "color": "green"
              },
              {
                "color": "red",
                "value": 80
              }
            ]
          },
          "unit": "short"
        },
        "overrides": []
      },
      "gridPos": {
        "h": 7,
        "w": 12,
        "x": 0,
        "y": 7
      },
      "id": 2,
      "maxDataPoints": "",
      "options": {
        "dataLinks": [],
        "legend": {
          "calcs": [],
          "displayMode": "list",
          "placement": "bottom",
          "showLegend": true
        },
        "tooltip": {
          "hideZeros": false,
          "mode": "multi",
          "sort": "none"
        }
      },
      "pluginVersion": "12.0.2",
      "targets": [
        {
          "datasource": {
            "type": "prometheus",
            "uid": "$${datasource}"
          },
          "expr": "bottomk(5,avi_healthscore_health_score_value{instance=~\"$instance\", tenant=~\"$tenant\",type=\"serviceengine\"})",
          "format": "time_series",
          "interval": "1m",
          "intervalFactor": 1,
          "legendFormat": "{{name}}",
          "refId": "A",
          "target": "aliasByNode(lowestAverage(sortByMinima(network-script.avi.$location.$environment.$device.serviceengine.*.healthscore), 5), 6)",
          "textEditor": false
        }
      ],
      "title": "Lowest 5 - SE Healthscores",
      "type": "timeseries"
    },
    {
      "datasource": {
        "type": "prometheus",
        "uid": "$${datasource}"
      },
      "fieldConfig": {
        "defaults": {
          "color": {
            "mode": "palette-classic"
          },
          "custom": {
            "axisBorderShow": false,
            "axisCenteredZero": false,
            "axisColorMode": "text",
            "axisLabel": "",
            "axisPlacement": "auto",
            "barAlignment": 0,
            "barWidthFactor": 0.6,
            "drawStyle": "line",
            "fillOpacity": 40,
            "gradientMode": "none",
            "hideFrom": {
              "legend": false,
              "tooltip": false,
              "viz": false
            },
            "insertNulls": false,
            "lineInterpolation": "linear",
            "lineWidth": 2,
            "pointSize": 5,
            "scaleDistribution": {
              "type": "linear"
            },
            "showPoints": "never",
            "spanNulls": true,
            "stacking": {
              "group": "A",
              "mode": "none"
            },
            "thresholdsStyle": {
              "mode": "off"
            }
          },
          "mappings": [],
          "thresholds": {
            "mode": "absolute",
            "steps": [
              {
                "color": "green"
              },
              {
                "color": "red",
                "value": 80
              }
            ]
          },
          "unit": "none"
        },
        "overrides": []
      },
      "gridPos": {
        "h": 7,
        "w": 12,
        "x": 12,
        "y": 7
      },
      "id": 3,
      "options": {
        "dataLinks": [],
        "legend": {
          "calcs": [],
          "displayMode": "list",
          "placement": "bottom",
          "showLegend": true
        },
        "tooltip": {
          "hideZeros": false,
          "mode": "single",
          "sort": "none"
        }
      },
      "pluginVersion": "12.0.2",
      "targets": [
        {
          "datasource": {
            "type": "prometheus",
            "uid": "$${datasource}"
          },
          "expr": "count(count by (name) ({instance=~\"$instance\", tenant=~\"$tenant\",type=\"serviceengine\"}))",
          "format": "time_series",
          "interval": "1m",
          "intervalFactor": 1,
          "legendFormat": "serviceengine",
          "refId": "A",
          "target": "aliasByNode(network-script.avi.$location.$environment.$device.serviceengine.count, 5)",
          "textEditor": true
        }
      ],
      "title": "Number of Service Engines",
      "type": "timeseries"
    },
    {
      "datasource": {
        "type": "prometheus",
        "uid": "$${datasource}"
      },
      "fieldConfig": {
        "defaults": {
          "color": {
            "mode": "palette-classic"
          },
          "custom": {
            "axisBorderShow": false,
            "axisCenteredZero": false,
            "axisColorMode": "text",
            "axisLabel": "",
            "axisPlacement": "auto",
            "barAlignment": 0,
            "barWidthFactor": 0.6,
            "drawStyle": "line",
            "fillOpacity": 0,
            "gradientMode": "none",
            "hideFrom": {
              "legend": false,
              "tooltip": false,
              "viz": false
            },
            "insertNulls": false,
            "lineInterpolation": "linear",
            "lineWidth": 1,
            "pointSize": 5,
            "scaleDistribution": {
              "type": "linear"
            },
            "showPoints": "never",
            "spanNulls": true,
            "stacking": {
              "group": "A",
              "mode": "none"
            },
            "thresholdsStyle": {
              "mode": "off"
            }
          },
          "mappings": [],
          "thresholds": {
            "mode": "absolute",
            "steps": [
              {
                "color": "green"
              },
              {
                "color": "red",
                "value": 80
              }
            ]
          },
          "unit": "short"
        },
        "overrides": []
      },
      "gridPos": {
        "h": 7,
        "w": 12,
        "x": 0,
        "y": 14
      },
      "id": 6,
      "options": {
        "dataLinks": [],
        "legend": {
          "calcs": [],
          "displayMode": "list",
          "placement": "bottom",
          "showLegend": true
        },
        "tooltip": {
          "hideZeros": false,
          "mode": "multi",
          "sort": "none"
        }
      },
      "pluginVersion": "12.0.2",
      "targets": [
        {
          "datasource": {
            "type": "prometheus",
            "uid": "$${datasource}"
          },
          "expr": "topk(10,avi_se_if_avg_rx_pkts{instance=~\"$instance\", tenant=~\"$tenant\",type=\"serviceengine\"})",
          "format": "time_series",
          "instant": false,
          "interval": "1m",
          "intervalFactor": 1,
          "legendFormat": "{{name}}",
          "refId": "A",
          "target": "aliasByNode(highestMax(network-script.avi.$location.$environment.$device.serviceengine.*.se_if_avg_rx_pkts, 10), 6)",
          "textEditor": false
        }
      ],
      "title": "SE RX PPS  - Top 10",
      "type": "timeseries"
    },
    {
      "datasource": {
        "type": "prometheus",
        "uid": "$${datasource}"
      },
      "fieldConfig": {
        "defaults": {
          "color": {
            "mode": "palette-classic"
          },
          "custom": {
            "axisBorderShow": false,
            "axisCenteredZero": false,
            "axisColorMode": "text",
            "axisLabel": "",
            "axisPlacement": "auto",
            "barAlignment": 0,
            "barWidthFactor": 0.6,
            "drawStyle": "line",
            "fillOpacity": 0,
            "gradientMode": "none",
            "hideFrom": {
              "legend": false,
              "tooltip": false,
              "viz": false
            },
            "insertNulls": false,
            "lineInterpolation": "linear",
            "lineWidth": 1,
            "pointSize": 5,
            "scaleDistribution": {
              "type": "linear"
            },
            "showPoints": "never",
            "spanNulls": true,
            "stacking": {
              "group": "A",
              "mode": "none"
            },
            "thresholdsStyle": {
              "mode": "off"
            }
          },
          "mappings": [],
          "thresholds": {
            "mode": "absolute",
            "steps": [
              {
                "color": "green"
              },
              {
                "color": "red",
                "value": 80
              }
            ]
          },
          "unit": "percent"
        },
        "overrides": []
      },
      "gridPos": {
        "h": 7,
        "w": 12,
        "x": 12,
        "y": 14
      },
      "id": 5,
      "options": {
        "dataLinks": [],
        "legend": {
          "calcs": [],
          "displayMode": "list",
          "placement": "bottom",
          "showLegend": true
        },
        "tooltip": {
          "hideZeros": false,
          "mode": "multi",
          "sort": "none"
        }
      },
      "pluginVersion": "12.0.2",
      "targets": [
        {
          "datasource": {
            "type": "prometheus",
            "uid": "$${datasource}"
          },
          "expr": "topk(10,avi_se_stats_avg_connection_mem_usage{instance=~\"$instance\", tenant=~\"$tenant\",type=\"serviceengine\"})",
          "format": "time_series",
          "interval": "1m",
          "intervalFactor": 1,
          "legendFormat": "{{name}}",
          "refId": "A",
          "target": "aliasByNode(highestCurrent(network-script.avi.$location.$environment.$device.serviceengine.*.se_stats_avg_connection_mem_usage, 10), 6)",
          "textEditor": true
        }
      ],
      "title": "Connection Memory Usage - Top 10",
      "type": "timeseries"
    },
    {
      "datasource": {
        "type": "prometheus",
        "uid": "$${datasource}"
      },
      "fieldConfig": {
        "defaults": {
          "color": {
            "mode": "palette-classic"
          },
          "custom": {
            "axisBorderShow": false,
            "axisCenteredZero": false,
            "axisColorMode": "text",
            "axisLabel": "",
            "axisPlacement": "auto",
            "barAlignment": 0,
            "barWidthFactor": 0.6,
            "drawStyle": "line",
            "fillOpacity": 10,
            "gradientMode": "none",
            "hideFrom": {
              "legend": false,
              "tooltip": false,
              "viz": false
            },
            "insertNulls": false,
            "lineInterpolation": "linear",
            "lineWidth": 2,
            "pointSize": 5,
            "scaleDistribution": {
              "type": "linear"
            },
            "showPoints": "never",
            "spanNulls": true,
            "stacking": {
              "group": "A",
              "mode": "none"
            },
            "thresholdsStyle": {
              "mode": "off"
            }
          },
          "mappings": [],
          "thresholds": {
            "mode": "absolute",
            "steps": [
              {
                "color": "green"
              },
              {
                "color": "red",
                "value": 80
              }
            ]
          },
          "unit": "short"
        },
        "overrides": []
      },
      "gridPos": {
        "h": 6,
        "w": 24,
        "x": 0,
        "y": 21
      },
      "id": 8,
      "options": {
        "dataLinks": [],
        "legend": {
          "calcs": [],
          "displayMode": "list",
          "placement": "bottom",
          "showLegend": true
        },
        "tooltip": {
          "hideZeros": false,
          "mode": "multi",
          "sort": "none"
        }
      },
      "pluginVersion": "12.0.2",
      "targets": [
        {
          "datasource": {
            "type": "prometheus",
            "uid": "$${datasource}"
          },
          "expr": "topk(10,avi_se_stats_avg_connections{instance=~\"$instance\", tenant=~\"$tenant\",type=\"serviceengine\"})",
          "format": "time_series",
          "interval": "1m",
          "intervalFactor": 1,
          "legendFormat": "{{name}}",
          "refId": "A",
          "target": "aliasByNode(highestCurrent(network-script.avi.$location.$environment.$device.serviceengine.*.se_stats_avg_connections, 10), 6)",
          "textEditor": true
        }
      ],
      "title": "SE CPS",
      "type": "timeseries"
    }
  ],
  "preload": false,
  "refresh": "1m",
  "schemaVersion": 41,
  "tags": [
    "avi"
  ],
  "templating": {
    "list": [
      {
        "allowCustomValue": false,
        "current": {
          "text": "victoria-metrics",
          "value": "victoria-metrics"
        },
        "label": "Data Source",
        "name": "datasource",
        "options": [],
        "query": "prometheus",
        "refresh": 1,
        "regex": "",
        "type": "datasource"
      },
      {
        "allValue": "*",
        "allowCustomValue": false,
        "current": {
          "text": "mdc1-tcp-avi",
          "value": "mdc1-tcp-avi"
        },
        "datasource": {
          "type": "prometheus",
          "uid": "$${datasource}"
        },
        "definition": "label_values({type=\"serviceengine\"},instance)",
        "includeAll": false,
        "name": "instance",
        "options": [],
        "query": {
          "qryType": 1,
          "query": "label_values({type=\"serviceengine\"},instance)",
          "refId": "PrometheusVariableQueryEditor-VariableQuery"
        },
        "refresh": 1,
        "regex": "",
        "type": "query"
      },
      {
        "allValue": "*",
        "current": {
          "text": [
            "admin"
          ],
          "value": [
            "admin"
          ]
        },
        "datasource": {
          "type": "prometheus",
          "uid": "$${datasource}"
        },
        "definition": "label_values({type=\"serviceengine\", instance=~\"$instance\"},tenant)",
        "includeAll": false,
        "multi": true,
        "name": "tenant",
        "options": [],
        "query": {
          "qryType": 1,
          "query": "label_values({type=\"serviceengine\", instance=~\"$instance\"},tenant)",
          "refId": "PrometheusVariableQueryEditor-VariableQuery"
        },
        "refresh": 1,
        "regex": "",
        "type": "query"
      }
    ]
  },
  "time": {
    "from": "now-3h",
    "to": "now"
  },
  "timepicker": {},
  "timezone": "browser",
  "title": "Avi-Service Engines Total",
  "uid": null,
  "version": 4
}